gcinvoice/__init__.py
gcinvoice/_version.py
gcinvoice/gcivc.py
gcinvoice/yaptu.py
gcinvoice-0.2.5.dist-info/LICENSE
gcinvoice-0.2.5.dist-info/METADATA
gcinvoice-0.2.5.dist-info/WHEEL
gcinvoice-0.2.5.dist-info/entry_points.txt
gcinvoice-0.2.5.dist-info/top_level.txt
gcinvoice-0.2.5.dist-info/RECORD
