Metadata-Version: 2.1
Name: gcinvoice
Version: 0.2.5
Summary: Parse Gnucash data and create invoices
Home-page: https://foss.heptapod.net/accounting/gcinvoice
Author: Roman Bertle
Author-email: bertle@smoerz.org
License: MIT License
Keywords: Gnucash reporting
Platform: UNKNOWN
Classifier: Development Status :: 3 - Alpha
Classifier: Intended Audience :: End Users/Desktop
Classifier: Intended Audience :: Financial and Insurance Industry
Classifier: Topic :: Office/Business :: Financial :: Accounting
Classifier: License :: OSI Approved :: MIT License
Classifier: Programming Language :: Python :: 2
Classifier: Programming Language :: Python :: 2.7
Classifier: Programming Language :: Python :: 3
Classifier: Environment :: Console
Requires-Dist: future ; python_version < "3.0"
